{
  "required": true,
  "package": "moffy.ticex.mixin",
  "compatibilityLevel": "JAVA_17",
  "refmap": "ticex.refmap.json",
  "mixins": [
    "CriticalAccessor",
    "MaterialCastingLookupMixin",
    "MeleeAttributeModuleMixin",
    "RomanNumeralHelperMixin",
    "config.AbstractCastingRecipeAccessor",
    "config.AbstractCastingRecipeMixin",
    "config.AbstractModifierRecipeAccessor",
    "config.AbstractModifierRecipeMixin",
    "config.MeltingFuelAccessor",
    "config.MeltingFuelMixin",
    "config.ToolDefinitionLoaderMixin"
  ],
  "client": [
  ],
  "server": [],
  "injectors": {
    "defaultRequire": 1
  },
  "minVersion": "0.7"
}
